shenanigans/__init__.py
shenanigans/morethreadstuff.py
shenanigans/nerdlib.py
shenanigans-0.0.2.dist-info/METADATA
shenanigans-0.0.2.dist-info/WHEEL
shenanigans-0.0.2.dist-info/top_level.txt
shenanigans-0.0.2.dist-info/RECORD
