Metadata-Version: 2.1
Name: shenanigans
Version: 0.0.2
Summary: Random utilities for great convienence.
Author: Noahlski
Author-email: noahc018@proton.me
Classifier: Programming Language :: Python :: 3
